LICENSE
MANIFEST.in
README.md
setup.py
lambda_config/__init__.py
lambda_config/__version__.py
lambda_config/config.py
lambda_config/utils.py
lambda_config.egg-info/PKG-INFO
lambda_config.egg-info/SOURCES.txt
lambda_config.egg-info/dependency_links.txt
lambda_config.egg-info/requires.txt
lambda_config.egg-info/top_level.txt