Metadata-Version: 2.1
Name: lambda-config
Version: 0.0.4
Summary: Retrieve config from SSM parameter store on lambda start
Home-page: https://github.com/niranjan94/lambda-config
Author: Niranjan Rajendran
Author-email: me@niranjan.io
License: MIT
Platform: UNKNOWN
Classifier: License :: OSI Approved :: MIT License
Classifier: Programming Language :: Python
Classifier: Programming Language :: Python :: 3
Classifier: Programming Language :: Python :: 3.6
Classifier: Programming Language :: Python :: 3.7
Classifier: Programming Language :: Python :: Implementation :: CPython
Classifier: Programming Language :: Python :: Implementation :: PyPy
Requires-Python: >=3.6.0
